soli_data_generator/__init__.py
soli_data_generator/llm/__init__.py
soli_data_generator/llm/text.py
soli_data_generator/procedural/__init__.py
soli_data_generator/procedural/template.py
soli_data_generator-0.1.1.dist-info/LICENSE
soli_data_generator-0.1.1.dist-info/METADATA
soli_data_generator-0.1.1.dist-info/WHEEL
soli_data_generator-0.1.1.dist-info/RECORD
