Metadata-Version: 2.1
Name: soli-data-generator
Version: 0.1.1
Summary: Python library for SOLI data generation
Home-page: https://openlegalstandard.org/
License: MIT
Keywords: legal,information,standard,soli,open
Author: ALEA Institute
Author-email: hello@aleainstitute.ai
Requires-Python: >=3.10,<4.0.0
Classifier: Development Status :: 3 - Alpha
Classifier: Intended Audience :: Developers
Classifier: Intended Audience :: Legal Industry
Classifier: Intended Audience :: Science/Research
Classifier: License :: OSI Approved :: MIT License
Classifier: Operating System :: OS Independent
Classifier: Programming Language :: Python
Classifier: Programming Language :: Python :: 3
Classifier: Programming Language :: Python :: 3.10
Classifier: Programming Language :: Python :: 3.11
Classifier: Programming Language :: Python :: 3.12
Classifier: Topic :: Scientific/Engineering :: Artificial Intelligence
Classifier: Topic :: Scientific/Engineering :: Information Analysis
Classifier: Topic :: Software Development :: Libraries :: Python Modules
Classifier: Topic :: Text Processing :: Markup :: XML
Classifier: Topic :: Utilities
Provides-Extra: search
Requires-Dist: alea-llm-client (>=0.1.0,<0.2.0)
Requires-Dist: faker (>=28.4.1,<29.0.0)
Requires-Dist: soli-python (>=0.1.4,<0.2.0)
Project-URL: Documentation, https://github.com/alea-institute/soli-data-generator
Project-URL: Repository, https://github.com/alea-institute/soli-data-generator
